Metadata-Version: 2.1
Name: pytest-chainmaker
Version: 0.1
Summary: pytest plugin for chainmaker
Home-page: https://github.com/hanzhichao/pytest-chainmaker
Author: Han Zhichao
Author-email: superhin@126.com
License: MIT license
Keywords: pytest,pytest-chainmaker,chainmaker,python-chainmaker
Platform: UNKNOWN
Classifier: Framework :: Pytest
Classifier: Programming Language :: Python
Classifier: Topic :: Software Development :: Testing
Classifier: Programming Language :: Python :: 2.7
Classifier: Programming Language :: Python :: 3.7
License-File: LICENSE
